odoo8_addon_base_ir_filters_active-8.0.1.0.0.99.dev21-py2.7-nspkg.pth
odoo8_addon_base_ir_filters_active-8.0.1.0.0.99.dev21.dist-info/DESCRIPTION.rst
odoo8_addon_base_ir_filters_active-8.0.1.0.0.99.dev21.dist-info/METADATA
odoo8_addon_base_ir_filters_active-8.0.1.0.0.99.dev21.dist-info/RECORD
odoo8_addon_base_ir_filters_active-8.0.1.0.0.99.dev21.dist-info/WHEEL
odoo8_addon_base_ir_filters_active-8.0.1.0.0.99.dev21.dist-info/metadata.json
odoo8_addon_base_ir_filters_active-8.0.1.0.0.99.dev21.dist-info/namespace_packages.txt
odoo8_addon_base_ir_filters_active-8.0.1.0.0.99.dev21.dist-info/top_level.txt
odoo_addons/base_ir_filters_active/README.rst
odoo_addons/base_ir_filters_active/__init__.py
odoo_addons/base_ir_filters_active/__openerp__.py
odoo_addons/base_ir_filters_active/i18n/ar.po
odoo_addons/base_ir_filters_active/i18n/base_ir_filters_active.pot
odoo_addons/base_ir_filters_active/i18n/bg.po
odoo_addons/base_ir_filters_active/i18n/bs.po
odoo_addons/base_ir_filters_active/i18n/ca.po
odoo_addons/base_ir_filters_active/i18n/cs.po
odoo_addons/base_ir_filters_active/i18n/da.po
odoo_addons/base_ir_filters_active/i18n/de.po
odoo_addons/base_ir_filters_active/i18n/en_GB.po
odoo_addons/base_ir_filters_active/i18n/es.po
odoo_addons/base_ir_filters_active/i18n/es_CR.po
odoo_addons/base_ir_filters_active/i18n/es_EC.po
odoo_addons/base_ir_filters_active/i18n/es_ES.po
odoo_addons/base_ir_filters_active/i18n/es_MX.po
odoo_addons/base_ir_filters_active/i18n/es_VE.po
odoo_addons/base_ir_filters_active/i18n/et.po
odoo_addons/base_ir_filters_active/i18n/fi.po
odoo_addons/base_ir_filters_active/i18n/fr.po
odoo_addons/base_ir_filters_active/i18n/fr_CH.po
odoo_addons/base_ir_filters_active/i18n/gl.po
odoo_addons/base_ir_filters_active/i18n/hr.po
odoo_addons/base_ir_filters_active/i18n/hr_HR.po
odoo_addons/base_ir_filters_active/i18n/hu.po
odoo_addons/base_ir_filters_active/i18n/id.po
odoo_addons/base_ir_filters_active/i18n/it.po
odoo_addons/base_ir_filters_active/i18n/ja.po
odoo_addons/base_ir_filters_active/i18n/lt.po
odoo_addons/base_ir_filters_active/i18n/mk.po
odoo_addons/base_ir_filters_active/i18n/mn.po
odoo_addons/base_ir_filters_active/i18n/nb.po
odoo_addons/base_ir_filters_active/i18n/nl.po
odoo_addons/base_ir_filters_active/i18n/nl_BE.po
odoo_addons/base_ir_filters_active/i18n/nl_NL.po
odoo_addons/base_ir_filters_active/i18n/pl.po
odoo_addons/base_ir_filters_active/i18n/pt.po
odoo_addons/base_ir_filters_active/i18n/pt_BR.po
